typegripe/__init__.py
typegripe/check.py
typegripe-0.1.0.dist-info/LICENSE
typegripe-0.1.0.dist-info/WHEEL
typegripe-0.1.0.dist-info/METADATA
typegripe-0.1.0.dist-info/RECORD
