Metadata-Version: 2.1
Name: typegripe
Version: 0.1.0
Summary: mypy tests for correct type annotations. typegripe complains if you didn't add any.
Author: Matt White
Author-email: code@typenil.com
Requires-Python: >=3.8,<4.0
Classifier: Programming Language :: Python :: 3
Classifier: Programming Language :: Python :: 3.8
Requires-Dist: loguru (>=0.5.1,<0.6.0)
